archivist/__init__.py
archivist/about.py
archivist/access_policies.py
archivist/appidp.py
archivist/applications.py
archivist/archivist.py
archivist/archivistpublic.py
archivist/asset.py
archivist/assetattachments.py
archivist/assets.py
archivist/attachments.py
archivist/compliance.py
archivist/compliance_policies.py
archivist/compliance_policy_requests.py
archivist/compliance_policy_type.py
archivist/composite.py
archivist/confirmer.py
archivist/constants.py
archivist/dictmerge.py
archivist/errors.py
archivist/events.py
archivist/headers.py
archivist/locations.py
archivist/logger.py
archivist/or_dict.py
archivist/parser.py
archivist/proof_mechanism.py
archivist/publisher.py
archivist/retry429.py
archivist/runner.py
archivist/sbommetadata.py
archivist/sboms.py
archivist/subjects.py
archivist/subjects_confirmer.py
archivist/tenancies.py
archivist/timestamp.py
archivist/uploader.py
archivist/utils.py
archivist/withdrawer.py
archivist/cmds/__init__.py
archivist/cmds/runner/__init__.py
archivist/cmds/runner/__main__.py
archivist/cmds/runner/main.py
archivist/cmds/runner/run.py
archivist/cmds/template/__init__.py
archivist/cmds/template/__main__.py
archivist/cmds/template/main.py
archivist/cmds/template/run.py
jitsuin_archivist-0.17.5.dist-info/LICENSE
jitsuin_archivist-0.17.5.dist-info/METADATA
jitsuin_archivist-0.17.5.dist-info/WHEEL
jitsuin_archivist-0.17.5.dist-info/entry_points.txt
jitsuin_archivist-0.17.5.dist-info/top_level.txt
jitsuin_archivist-0.17.5.dist-info/RECORD
