Metadata-Version: 2.1
Name: jitsuin-archivist
Version: 0.17.5
Summary: RKVST Client
Home-page: https://github.com/jitsuin-inc/archivist-python
Author: RKVST Inc.
Author-email: support@rkvst.com
License: MIT
Project-URL: Documentation, https://python.rkvst.com
Project-URL: Source, https://github.com/jitsuin-inc/archivist-python
Project-URL: Tracker, https://github.com/jitsuin-inc/archivist-python/issues
Classifier: Development Status :: 3 - Alpha
Classifier: Environment :: Console
Classifier: Intended Audience :: Developers
Classifier: License :: OSI Approved :: MIT License
Classifier: Operating System :: POSIX :: Linux
Classifier: Programming Language :: Python :: 3.7
Classifier: Topic :: Utilities
Requires-Python: >=3.7
License-File: LICENSE
Requires-Dist: backoff (~=1.11)
Requires-Dist: certifi
Requires-Dist: flatten-dict (~=0.4)
Requires-Dist: iso8601 (~=1.0)
Requires-Dist: Jinja2 (~=3.0)
Requires-Dist: pyaml-env (~=1.1)
Requires-Dist: requests (~=2.28)
Requires-Dist: requests-toolbelt (~=0.9)
Requires-Dist: rfc3339 (~=6.2)
Requires-Dist: xmltodict (~=0.13)
